LICENSE
mkdocs_git_tag_plugin/__init__.py
mkdocs_git_tag_plugin/plugin.py
mkdocs_git_tag_plugin-0.1.0.dist-info/entry_points.txt
mkdocs_git_tag_plugin-0.1.0.dist-info/LICENSE
mkdocs_git_tag_plugin-0.1.0.dist-info/WHEEL
mkdocs_git_tag_plugin-0.1.0.dist-info/METADATA
mkdocs_git_tag_plugin-0.1.0.dist-info/RECORD
